django_started_toolkit/__init__.py
django_started_toolkit/forms.py
django_started_toolkit/utils.py
django_started_toolkit/static/django_started_tollkit/css/sidebar.css
django_started_toolkit/static/django_started_tollkit/css/sidebar_admin.css
django_started_toolkit/static/django_started_tollkit/css/sidebar_perfil.css
django_started_toolkit/static/django_started_tollkit/css/style.css
django_started_toolkit/static/django_started_tollkit/js/functions.js
django_started_toolkit/static/django_started_tollkit/js/iconpicker.js
django_started_toolkit/static/django_started_tollkit/js/sidebar.js
django_started_toolkit/static/django_started_tollkit/js/sidebar_perfil.js
django_started_toolkit-0.1.0.dist-info/LICENSE
django_started_toolkit-0.1.0.dist-info/METADATA
django_started_toolkit-0.1.0.dist-info/WHEEL
django_started_toolkit-0.1.0.dist-info/top_level.txt
django_started_toolkit-0.1.0.dist-info/RECORD
