Metadata-Version: 2.2
Name: django-started-toolkit
Version: 0.1.0
Summary: Un toolkit con utilidades y helpers para Django, que incluye formularios, funciones JS y utilidades generales.
Home-page: https://github.com/tuusuario/django-started-toolkit
Author: Tu Nombre
Author-email: tu.email@example.com
Classifier: Programming Language :: Python :: 3
Classifier: Framework :: Django
Classifier: License :: OSI Approved :: MIT License
License-File: LICENSE
Requires-Dist: Django>=2.2
Requires-Dist: requests
Requires-Dist: pandas
Requires-Dist: beautifulsoup4
Requires-Dist: firebase-admin
Requires-Dist: pymongo
Dynamic: author
Dynamic: author-email
Dynamic: classifier
Dynamic: description
Dynamic: description-content-type
Dynamic: home-page
Dynamic: requires-dist
Dynamic: summary
